siglib/__init__.py
siglib/siglib.py
siglib-0.1.0.dist-info/METADATA
siglib-0.1.0.dist-info/WHEEL
siglib-0.1.0.dist-info/top_level.txt
siglib-0.1.0.dist-info/RECORD
