Metadata-Version: 2.1
Name: siglib
Version: 0.1.0
Summary: UNKNOWN
Home-page: https://github.com/kyjohnso/siglib
Maintainer: Kyle Johnson
License: UNKNOWN
Platform: UNKNOWN
Requires-Dist: numba
Requires-Dist: numpy
